dime_sampler/__init__.py
dime_sampler/__version__.py
dime_sampler/moves.py
dime_sampler/test_all.py
dime_sampler/test_storage/median.npy
dime_sampler-1.0.0.dist-info/LICENSE
dime_sampler-1.0.0.dist-info/METADATA
dime_sampler-1.0.0.dist-info/WHEEL
dime_sampler-1.0.0.dist-info/top_level.txt
dime_sampler-1.0.0.dist-info/RECORD
