Metadata-Version: 2.1
Name: dime_sampler
Version: 1.0.0
Summary: DIME MCMC sampling for python
Home-page: https://github.com/gboehl/dime_sampler
Author: Gregor Boehl
Author-email: admin@gregorboehl.com
License: MIT
Classifier: License :: OSI Approved :: MIT License
Classifier: Programming Language :: Python :: 3
Classifier: Programming Language :: Python :: 3.11
License-File: LICENSE
Requires-Dist: numpy
Requires-Dist: scipy
Requires-Dist: emcee
